README.rst
setup.py
dominfo/__init__.py
framework/Host_Info_Tracker.py
framework/__init__.py
framework/nodeinfo.xml
framework/nodeinfo_parser.py
framework/vmonere.py
framework/vmonere_command_line_utility.py
graph/__init__.py
graph/jars/__init__.py
graph/jars/cpumonitor.jar
graph/jars/iomonitor.jar
graph/jars/memorymonitor.jar
graph/jars/vmmonitor.jar
graph/java/CPUMonitoringGraph.java
graph/java/IOMonitoringGraph.java
graph/java/MainPanel.java
graph/java/MemoryMonitoringGraph.java
graph/java/ValidationMessage.java
graph/java/__init__.py
guest/__init__.py
guest/host_config.txt
guest/timeout.py
guest/vmonere_agent.py
guest/vmonere_utility.py
host/__init__.py
host/start_host_monitor_process.py
host/timeout.py
host/vmonere_exec_log_deleter.py
host/vmonere_host_sender.socket
host/vmonere_listener.py
host/vmonere_log_deleter.sh
host/vmonere_monitorgraph.py
host/vmonere_start_monitor.py
host/vmonere_utility.py
host/write_log.py
hostinfo/__init__.py
hostinfo/host_config.txt
hostinfo/node1.txt
hostinfo/node2.txt
hostinfo/node3.txt
hostinfo/node4.txt
monitor/__init__.py
monitor/run_init.sh
monitor_logs/__init__.py
monitor_logs/domain/__init__.py
monitor_logs/host/__init__.py
monitor_logs/json/__init__.py
sockets/__init__.py
sockets/vmonere_host_listener.socket
sockets/vmonere_host_sender.socket
sockets/vmonere_listener.socket.py
sockets/vmonere_sender.socket.py
usr_bin/__init__.py
usr_bin/vmonere.py
vmonere.egg-info/PKG-INFO
vmonere.egg-info/SOURCES.txt
vmonere.egg-info/dependency_links.txt
vmonere.egg-info/entry_points.txt
vmonere.egg-info/requires.txt
vmonere.egg-info/top_level.txt