Metadata-Version: 1.1
Name: vmonere
Version: 0.1.1
Summary: A high-level Python  CLI for virtual machine monitoring
Home-page: http://dcsolvere.github.io/vmonere/
Author: Dinesh Appavoo
Author-email: dinesha.cit@gmail.com
License: MIT
Keywords: monitor
Platform: UNKNOWN
Classifier: Development Status :: 3 - Alpha
Classifier: Intended Audience :: Developers
Classifier: Topic :: Software Development :: Build Tools
Classifier: License :: OSI Approved :: MIT License
Classifier: Programming Language :: Python :: 2
Classifier: Programming Language :: Python :: 2.6
Classifier: Programming Language :: Python :: 2.7
